MANIFEST.in
README.rst
setup.py
vim_plugin_starter_kit/__init__.py
vim_plugin_starter_kit/create_plugin_scaffold.py
vim_plugin_starter_kit.egg-info/PKG-INFO
vim_plugin_starter_kit.egg-info/SOURCES.txt
vim_plugin_starter_kit.egg-info/dependency_links.txt
vim_plugin_starter_kit.egg-info/entry_points.txt
vim_plugin_starter_kit.egg-info/not-zip-safe
vim_plugin_starter_kit.egg-info/top_level.txt
vim_plugin_starter_kit/templates/README.md
vim_plugin_starter_kit/templates/template.py
vim_plugin_starter_kit/templates/template.vim
vim_plugin_starter_kit/templates/doc/template.txt
vim_plugin_starter_kit/templates/tests/__init__.py
vim_plugin_starter_kit/templates/tests/template_tests.py
vim_plugin_starter_kit/tests/__init__.py
vim_plugin_starter_kit/tests/assertions.py
vim_plugin_starter_kit/tests/file_specific_tests.py
vim_plugin_starter_kit/tests/mixins.py
vim_plugin_starter_kit/tests/non_file_specific_tests.py
vim_plugin_starter_kit/tests/custom_docs/README.md
vim_plugin_starter_kit/tests/custom_docs/__init__.py
vim_plugin_starter_kit/tests/custom_docs/vim-tests.txt
vim_plugin_starter_kit/tests/custom_docs/vim_tests.py
vim_plugin_starter_kit/tests/custom_docs/vim_tests.vim
vim_plugin_starter_kit/tests/custom_docs/vim_tests_tests.py