Metadata-Version: 1.1
Name: vim-plugin-starter-kit
Version: 1.0.0
Summary: A tool that creates a scafold for Vim plugins to be written in Python.
Home-page: http://github.com/JarrodCTaylor/vim-plugin-starter-kit
Author: Jarrod C. Taylor
Author-email: jarrod.c.taylor@gmail.com
License: MIT
Platform: UNKNOWN
Classifier: Topic :: Text Editors
Classifier: Intended Audience :: Developers
